[
  {
    "Id": 0,
    "Username": "mrbean@teacher.uni.edu",
    "DefinitelyNotPasswordHash": "templatepasswordhash",
    "Name": "Mr.",
    "Surname": "Bean"
  },
  {
    "Id": 1,
    "Username": "ironman@teacher.uni.edu",
    "DefinitelyNotPasswordHash": "templatepasswordhash",
    "Name": "iron",
    "Surname": "man"
  },
  {
    "Id": 2,
    "Username": "robertkalinak@teacher.uni.edu",
    "DefinitelyNotPasswordHash": "templatepasswordhash",
    "Name": "Robert",
    "Surname": "Kalinak"
  },

  {
    "Id": 3,
    "Username": "test",
    "DefinitelyNotPasswordHash": "test",
    "Name": "Robert",
    "Surname": "Kalinak"
  }
]
